ros2_lifecycle_package_creator/__init__.py
ros2_lifecycle_package_creator/generate_cmakelists.py
ros2_lifecycle_package_creator/generate_launch.py
ros2_lifecycle_package_creator/generate_package_xml.py
ros2_lifecycle_package_creator/generate_readme.py
ros2_lifecycle_package_creator/generate_source.py
ros2_lifecycle_package_creator/main.py
ros2_lifecycle_package_creator/package_files/.clang-format
ros2_lifecycle_package_creator/package_generator.py
ros2_lifecycle_package_creator/templates/cmakelists.j2
ros2_lifecycle_package_creator/templates/node_cpp.j2
ros2_lifecycle_package_creator/templates/node_hpp.j2
ros2_lifecycle_package_creator/templates/node_launch.j2
ros2_lifecycle_package_creator/templates/node_main.j2
ros2_lifecycle_package_creator/templates/package_xml.j2
ros2_lifecycle_package_creator/templates/readme.j2
ros2_lifecycle_package_creator/utils.py
ros2_lifecycle_package_creator-0.1.4.dist-info/METADATA
ros2_lifecycle_package_creator-0.1.4.dist-info/WHEEL
ros2_lifecycle_package_creator-0.1.4.dist-info/entry_points.txt
ros2_lifecycle_package_creator-0.1.4.dist-info/RECORD
