Metadata-Version: 2.3
Name: ros2-lifecycle-package-creator
Version: 0.1.4
Summary: Create ROS2 lifecycle package boilerplate from a minimal config file
License: Apache-2.0
Author: Myron Rodrigues
Author-email: rodriguesmyron47@gmail.com
Requires-Python: >=3.8,<4.0
Classifier: License :: OSI Approved :: Apache Software License
Classifier: Programming Language :: Python :: 3
Classifier: Programming Language :: Python :: 3.8
Classifier: Programming Language :: Python :: 3.9
Classifier: Programming Language :: Python :: 3.10
Classifier: Programming Language :: Python :: 3.11
Classifier: Programming Language :: Python :: 3.12
Classifier: Programming Language :: Python :: 3.13
Requires-Dist: Jinja2 (>=3.1.4,<4.0.0)
Requires-Dist: pyyaml (>=6.0.1,<7.0.0)
